{
  "generator-jhipster": {
    "applicationType": "monolith",
    "authenticationType": "jwt",
    "baseName": "db",
    "blueprints": [],
    "buildTool": "gradle",
    "cacheProvider": "ehcache",
    "clientFramework": "no",
    "clientPackageManager": "npm",
    "clientTheme": "none",
    "clientThemeVariant": "",
    "creationTimestamp": 1646622680011,
    "databaseType": "sql",
    "devDatabaseType": "h2Disk",
    "devServerPort": 9060,
    "dtoSuffix": "DTO",
    "enableGradleEnterprise": false,
    "enableHibernateCache": true,
    "enableSwaggerCodegen": false,
    "enableTranslation": false,
    "entitySuffix": "",
    "jhiPrefix": "jhi",
    "jhipsterVersion": "7.7.0",
    "jwtSecretKey": "YTgyMmIzNDk2M2QxODYwZmJlMGQ4OTJhYWMwYmIwNWUzZTgzMmQ4MjcyZDFhOTU5MGNhMzRhZTc3ZDRkNGY5Mzc3NDU1MGZhMWZiZDA1ZTY2OWZmOTA5MTdlZmE5MDkzYmE0MTUyYmFhOWZhODljOWUyNDIwN2RhMWZjNDY1ZjQ=",
    "languages": ["en", "fr"],
    "messageBroker": false,
    "nativeLanguage": "zh-cn",
    "otherModules": [],
    "packageName": "com.ledar.db",
    "pages": [],
    "prodDatabaseType": "postgresql",
    "reactive": false,
    "searchEngine": false,
    "serverPort": "8080",
    "serverSideOptions": [],
    "serviceDiscoveryType": "no",
    "skipCheckLengthOfIdentifier": false,
    "skipClient": true,
    "skipFakeData": false,
    "skipUserManagement": false,
    "testFrameworks": [],
    "websocket": false,
    "withAdminUi": true
  }
}
